geo_selector/__init__.py
geo_selector/frontend/build/asset-manifest.json
geo_selector/frontend/build/bootstrap.min.css
geo_selector/frontend/build/geo_selector.css
geo_selector/frontend/build/index.html
geo_selector/frontend/build/precache-manifest.e5ee775225f318b1b68d4af5dc842698.js
geo_selector/frontend/build/service-worker.js
geo_selector/frontend/build/static/css/2.e315e6af.chunk.css
geo_selector/frontend/build/static/css/2.e315e6af.chunk.css.map
geo_selector/frontend/build/static/js/2.06e1f43a.chunk.js
geo_selector/frontend/build/static/js/2.06e1f43a.chunk.js.LICENSE.txt
geo_selector/frontend/build/static/js/2.06e1f43a.chunk.js.map
geo_selector/frontend/build/static/js/main.ede1dee9.chunk.js
geo_selector/frontend/build/static/js/main.ede1dee9.chunk.js.map
geo_selector/frontend/build/static/js/runtime-main.11ec9aca.js
geo_selector/frontend/build/static/js/runtime-main.11ec9aca.js.map
geo_selector/frontend/build/static/media/markers-soft.79148a43.png
geo_selector/frontend/build/static/media/markers-soft@2x.0f2c1025.png
streamlit_geo_selector-0.1.0.dist-info/LICENSE
streamlit_geo_selector-0.1.0.dist-info/METADATA
streamlit_geo_selector-0.1.0.dist-info/WHEEL
streamlit_geo_selector-0.1.0.dist-info/top_level.txt
streamlit_geo_selector-0.1.0.dist-info/RECORD
