Metadata-Version: 2.1
Name: streamlit-geo-selector
Version: 0.1.0
Summary: Streamlit Leaflet component that allows user to place marker on map and return coordinates.
Home-page: UNKNOWN
Author: Collin Smith
Author-email: 
License: UNKNOWN
Platform: UNKNOWN
Requires-Python: >=3.6
License-File: LICENSE
Requires-Dist: streamlit (>=0.63)
